taichi_elements/__init__.py
taichi_elements/mpm_solver.py
taichi_elements/voxelizer.py
taichi_elements-0.0.1.dist-info/METADATA
taichi_elements-0.0.1.dist-info/WHEEL
taichi_elements-0.0.1.dist-info/top_level.txt
taichi_elements-0.0.1.dist-info/RECORD
